opencpaas_twilio/__init__.py
opencpaas_twilio/twilio.py
opencpaas_twilio-0.0.2.dist-info/LICENSE
opencpaas_twilio-0.0.2.dist-info/METADATA
opencpaas_twilio-0.0.2.dist-info/WHEEL
opencpaas_twilio-0.0.2.dist-info/top_level.txt
opencpaas_twilio-0.0.2.dist-info/RECORD
