Metadata-Version: 2.1
Name: opencpaas-twilio
Version: 0.0.2
Summary: A Twilio implementation of OpenCpaas, an SDK that allows flexibility between CPaaS providers.
Home-page: https://github.com/Bandwidth/OpenCpaas/
Author: Perri Smith
Author-email: dx@bandwidth.com
License: UNKNOWN
Platform: UNKNOWN
Classifier: Programming Language :: Python :: 3
Classifier: License :: OSI Approved :: MIT License
Classifier: Operating System :: OS Independent
Requires-Dist: certifi
Requires-Dist: chardet
Requires-Dist: idna
Requires-Dist: opencpaas
Requires-Dist: PyJWT
Requires-Dist: PySocks
Requires-Dist: pytz
Requires-Dist: requests
Requires-Dist: six
Requires-Dist: twilio
Requires-Dist: urllib3
